[
  {
    "Symbol" : "ZRX",
    "TotalAmount" : 400000,
    "Amount" : 40000,
    "BuyRate" : 8,
    "SellRate" : 5
  },
  {
    "Symbol" : "LPT",
    "TotalAmount" : 400000,
    "Amount" : 40000,
    "BuyRate" : 8,
    "SellRate" : 5
  },
  {
    "Symbol" : "IQ",
    "TotalAmount" : 400000,
    "Amount" : 40000,
    "BuyRate" : 8,
    "SellRate" : 5
  },
  {
    "Symbol" : "ZRO",
    "TotalAmount" : 400000,
    "Amount" : 40000,
    "BuyRate" : 8,
    "SellRate" : 5
  },
  {
    "Symbol" : "CRTS",
    "TotalAmount" : 400000,
    "Amount" : 40000,
    "BuyRate" : 8,
    "SellRate" : 5
  },
  {
    "Symbol" : "VIRTUAL",
    "TotalAmount" : 400000,
    "Amount" : 40000,
    "BuyRate" : 8,
    "SellRate" : 5
  },
  {
    "Symbol" : "BLAST",
    "TotalAmount" : 400000,
    "Amount" : 40000,
    "BuyRate" : 8,
    "SellRate" : 5
  },
  {
    "Symbol" : "EIGEN",
    "TotalAmount" : 400000,
    "Amount" : 40000,
    "BuyRate" : 8,
    "SellRate" : 5
  },
  {
    "Symbol" : "TAIKO",
    "TotalAmount" : 400000,
    "Amount" : 40000,
    "BuyRate" : 8,
    "SellRate" : 5
  },
  {
    "Symbol" : "OSMO",
    "TotalAmount" : 400000,
    "Amount" : 40000,
    "BuyRate" : 8,
    "SellRate" : 5
  },
  {
    "Symbol" : "YFI",
    "TotalAmount" : 400000,
    "Amount" : 40000,
    "BuyRate" : 8,
    "SellRate" : 5
  },
  {
    "Symbol" : "IO",
    "TotalAmount" : 400000,
    "Amount" : 40000,
    "BuyRate" : 8,
    "SellRate" : 5
  },
  {
    "Symbol" : "AAVE",
    "TotalAmount" : 400000,
    "Amount" : 40000,
    "BuyRate" : 8,
    "SellRate" : 5
  },
  {
    "Symbol" : "FET",
    "TotalAmount" : 400000,
    "Amount" : 40000,
    "BuyRate" : 8,
    "SellRate" : 5
  },
  {
    "Symbol" : "ZK",
    "TotalAmount" : 400000,
    "Amount" : 40000,
    "BuyRate" : 8,
    "SellRate" : 5
  },
  {
    "Symbol" : "SUSHI",
    "TotalAmount" : 400000,
    "Amount" : 40000,
    "BuyRate" : 8,
    "SellRate" : 5
  },
  {
    "Symbol" : "CELR",
    "TotalAmount" : 400000,
    "Amount" : 40000,
    "BuyRate" : 8,
    "SellRate" : 5
  }
]

